check_filemaker.py
check_filemaker-0.2.2.dist-info/DESCRIPTION.rst
check_filemaker-0.2.2.dist-info/METADATA
check_filemaker-0.2.2.dist-info/metadata.json
check_filemaker-0.2.2.dist-info/RECORD
check_filemaker-0.2.2.dist-info/top_level.txt
check_filemaker-0.2.2.dist-info/WHEEL
