Metadata-Version: 2.0
Name: check-filemaker
Version: 0.2.2
Summary: Nagios plugin for monitoring FileMaker
Home-page: https://github.com/basictheprogram/check_filemaker
Author: Bob Tanner
Author-email: tanner@real-time.com
License: GPL
Download-URL: http://pypi.python.org/pypi/check_filemaker
Keywords: Nagios plugin monitoring FileMaker
Platform: UNKNOWN
Classifier: Development Status :: 4 - Beta
Classifier: Environment :: Plugins
Classifier: Intended Audience :: Developers
Classifier: Intended Audience :: System Administrators
Classifier: License :: OSI Approved :: GNU General Public License v2 (GPLv2)
Classifier: Operating System :: POSIX :: Linux
Classifier: Operating System :: POSIX
Classifier: Programming Language :: Python :: 2.6
Classifier: Programming Language :: Python :: 2.7
Classifier: Topic :: Software Development :: Libraries :: Python Modules
Classifier: Topic :: System :: Monitoring
Requires-Dist: PyFileMaker
Requires-Dist: requests
